[
  35,
  {
    "query": "",
    "id": {
      "title": "title title",
      "text": "text text",
      "id": "0"
    }
  },
  {
    "query": "",
    "id": null
  },
  {
    "query": "",
    "id": null
  },
  {
    "query": "",
    "id": null
  },
  {
    "query": "",
    "id": null
  },
  {
    "query": "",
    "id": null
  },
  {
    "query": "",
    "id": null
  },
  {
    "query": "",
    "id": null
  },
  {
    "query": "",
    "id": 1
  },
  {
    "query": "",
    "id": 2
  },
  {
    "query": "",
    "id": 3
  },
  {
    "query": "",
    "id": 4
  },
  {
    "query": "",
    "id": 5
  },
  {
    "query": "",
    "id": 6
  },
  {
    "query": "",
    "id": 7
  },
  {
    "query": "",
    "id": 8
  },
  {
    "query": "",
    "id": 9
  },
  {
    "query": "",
    "id": 10
  },
  {
    "query": "",
    "id": 11
  },
  {
    "query": "",
    "id": 12
  },
  {
    "query": "",
    "id": 13
  },
  {
    "query": "",
    "id": 14
  },
  {
    "query": "",
    "id": 15
  },
  {
    "query": "",
    "id": 16
  },
  {
    "query": "",
    "id": 17
  },
  {
    "query": "",
    "id": 18
  },
  {
    "query": "",
    "id": 19
  },
  {
    "query": "",
    "id": 20
  },
  {
    "query": "",
    "id": 21
  },
  {
    "query": "",
    "id": 22
  },
  {
    "query": "",
    "id": 23
  },
  {
    "query": "",
    "id": 24
  },
  {
    "query": "",
    "id": 25
  },
  {
    "query": "",
    "id": 26
  },
  {
    "title": "",
    "id": 27
  },
  {
    "title": "",
    "id": 28
  },
  {
    "title": "",
    "id": 29
  },
  {
    "title": "",
    "id": 30
  },
  {
    "title": "",
    "id": 31
  },
  {
    "title": "",
    "id": 32
  },
  {
    "title": "",
    "id": 33
  },
  {
    "title": "",
    "id": 34
  }
]